confidence-0.17.1.dist-info/METADATA
confidence-0.17.1.dist-info/WHEEL
confidence-0.17.1.dist-info/entry_points.txt
confidence-0.17.1.dist-info/licenses/LICENSE
confidence/__init__.py
confidence/exceptions.py
confidence/formats.py
confidence/io.py
confidence/models.py
confidence/utils.py
confidence-0.17.1.dist-info/RECORD
