Metadata-Version: 2.4
Name: confidence
Version: 0.17.1
Summary: Simple module to load and use configuration in a clean, 'pythonic' way.
Keywords: configuration
Author-Email: Netherlands Forensic Institute <netherlandsforensicinstitute@users.noreply.github.com>
License-Expression: Apache-2.0
Classifier: Programming Language :: Python
Classifier: Programming Language :: Python :: 3.10
Classifier: Programming Language :: Python :: 3.11
Classifier: Programming Language :: Python :: 3.12
Classifier: Programming Language :: Python :: 3.13
Classifier: Programming Language :: Python :: 3.14
Classifier: Topic :: Utilities
Project-URL: homepage, https://github.com/NetherlandsForensicInstitute/confidence/
Requires-Python: >=3.10
Requires-Dist: tomlkit>=0.13.3
Requires-Dist: pyyaml>=6.0
